h2m/__init__.py
h2m/h2m.py
h2m-0.2.0.dist-info/AUTHORS.rst
h2m-0.2.0.dist-info/LICENSE
h2m-0.2.0.dist-info/METADATA
h2m-0.2.0.dist-info/WHEEL
h2m-0.2.0.dist-info/top_level.txt
h2m-0.2.0.dist-info/RECORD
