Metadata-Version: 2.1
Name: h2m
Version: 0.2.0
Summary: simple and flexible html to markdown python converter
Home-page: https://github.com/goooice/h2m
Author: goooice
Author-email: devel0per1991@outlook.com
License: MIT license
Keywords: h2m
Platform: UNKNOWN
Classifier: Development Status :: 4 - Beta
Classifier: Intended Audience :: Developers
Classifier: License :: OSI Approved :: MIT License
Classifier: Natural Language :: English
Classifier: Programming Language :: Python :: 3.7
Classifier: Programming Language :: Python :: 3.8
Requires-Python: >=3.7
